LICENSE
MANIFEST.in
README.md
chainerx_build_helper.py
setup.cfg
setup.py
chainer/__init__.py
chainer/_backend.py
chainer/_backprop.py
chainer/_backprop_utils.py
chainer/_environment_check.py
chainer/_runtime_info.py
chainer/_version.py
chainer/backend.py
chainer/computational_graph.py
chainer/configuration.py
chainer/cuda.py
chainer/device_resident.py
chainer/distribution.py
chainer/function.py
chainer/function_hook.py
chainer/function_node.py
chainer/gradient_check.py
chainer/initializer.py
chainer/link.py
chainer/link_hook.py
chainer/memory_layouts.py
chainer/optimizer.py
chainer/reporter.py
chainer/sequential.py
chainer/serializer.py
chainer/types.py
chainer/variable.py
chainer/warnings.py
chainer.egg-info/PKG-INFO
chainer.egg-info/SOURCES.txt
chainer.egg-info/dependency_links.txt
chainer.egg-info/not-zip-safe
chainer.egg-info/requires.txt
chainer.egg-info/top_level.txt
chainer/backends/__init__.py
chainer/backends/_chainerx.py
chainer/backends/_cpu.py
chainer/backends/cuda.py
chainer/backends/intel64.py
chainer/dataset/__init__.py
chainer/dataset/convert.py
chainer/dataset/dataset_mixin.py
chainer/dataset/download.py
chainer/dataset/iterator.py
chainer/dataset/tabular/__init__.py
chainer/dataset/tabular/_asmode.py
chainer/dataset/tabular/_concat.py
chainer/dataset/tabular/_join.py
chainer/dataset/tabular/_slice.py
chainer/dataset/tabular/_transform.py
chainer/dataset/tabular/_with_converter.py
chainer/dataset/tabular/delegate_dataset.py
chainer/dataset/tabular/from_data.py
chainer/dataset/tabular/tabular_dataset.py
chainer/datasets/__init__.py
chainer/datasets/_mnist_helper.py
chainer/datasets/cifar.py
chainer/datasets/concatenated_dataset.py
chainer/datasets/dict_dataset.py
chainer/datasets/fashion_mnist.py
chainer/datasets/image_dataset.py
chainer/datasets/kuzushiji_mnist.py
chainer/datasets/mnist.py
chainer/datasets/pickle_dataset.py
chainer/datasets/ptb.py
chainer/datasets/sub_dataset.py
chainer/datasets/svhn.py
chainer/datasets/text_dataset.py
chainer/datasets/transform_dataset.py
chainer/datasets/tuple_dataset.py
chainer/distributions/__init__.py
chainer/distributions/bernoulli.py
chainer/distributions/beta.py
