Metadata-Version: 2.1
Name: chainer
Version: 7.0.0.post1
Summary: A flexible framework of neural networks
Home-page: https://chainer.org/
Author: Seiya Tokui
Author-email: tokui@preferred.jp
License: MIT License
Platform: UNKNOWN
Requires-Python: >=3.5.0
Provides-Extra: stylecheck
Provides-Extra: docs
Provides-Extra: appveyor
Provides-Extra: jenkins
Provides-Extra: doctest
Provides-Extra: test
